jax_plugins/xla_cuda12/__init__.py
jax_plugins/xla_cuda12/version.py
jax_plugins/xla_cuda12/xla_cuda_plugin.so
jax_cuda12_pjrt-0.9.0.dist-info/METADATA
jax_cuda12_pjrt-0.9.0.dist-info/WHEEL
jax_cuda12_pjrt-0.9.0.dist-info/entry_points.txt
jax_cuda12_pjrt-0.9.0.dist-info/top_level.txt
jax_cuda12_pjrt-0.9.0.dist-info/RECORD
