Metadata-Version: 2.4
Name: jax-cuda12-pjrt
Version: 0.9.0
Summary: JAX XLA PJRT Plugin for NVIDIA GPUs
Home-page: https://github.com/jax-ml/jax
Author: JAX team
Author-email: jax-dev@google.com
License: Apache-2.0
Classifier: Development Status :: 5 - Production/Stable
Classifier: Programming Language :: Python :: 3
Classifier: Programming Language :: Python :: Free Threading :: 3 - Stable
Dynamic: author
Dynamic: author-email
Dynamic: classifier
Dynamic: description-content-type
Dynamic: home-page
Dynamic: license
Dynamic: summary
